pytex2svg/__init__.py
pytex2svg-0.0.1.data/scripts/pytex2svg
pytex2svg-0.0.1.dist-info/LICENSE
pytex2svg-0.0.1.dist-info/METADATA
pytex2svg-0.0.1.dist-info/WHEEL
pytex2svg-0.0.1.dist-info/top_level.txt
pytex2svg-0.0.1.dist-info/RECORD
