Metadata-Version: 2.1
Name: pytex2svg
Version: 0.0.1
Summary: A simple command line tool to convert TeX equations to SVG.
Home-page: http://github.com/iuvbio/pytex2svg
Author: iuvbio
Author-email: lyndonbjohn@gmail.com
License: GPLv3+
Keywords: svg tex vector graphics convert
Platform: UNKNOWN
Classifier: Development Status :: 3 - Alpha
Classifier: License :: OSI Approved :: GNU General Public License v3 or later (GPLv3+)
Classifier: Programming Language :: Python :: 3.7
Classifier: Topic :: Utilities
Classifier: Operating System :: OS Independent
Requires-Dist: matplotlib
